{"id":"style.scss","dependencies":[{"name":"C:\\Users\\Administrator\\package.json","includedInParent":true,"mtime":1639909374046},{"name":"_css_loader","parent":"C:\\Users\\Administrator\\Desktop\\doraemon2.0\\src\\style.scss","resolved":"C:\\Users\\Administrator\\AppData\\Local\\Yarn\\Data\\global\\node_modules\\parcel\\src\\builtins\\css-loader.js"}],"generated":{"css":"* {\n  margin: 0;\n  padding: 0;\n  box-sizing: border-box; }\n\nbody {\n  display: flex;\n  flex-direction: column;\n  height: 100vh;\n  background-color: #1B94DD;\n  cursor: pointer;\n  overflow: hidden; }\n  body .code-box {\n    height: 46vh;\n    padding: 10px;\n    background-color: white;\n    border: 1px solid black; }\n    body .code-box #code {\n      overflow: hidden;\n      height: 40vh;\n      position: relative; }\n    body .code-box .button {\n      position: absolute;\n      top: 20px;\n      right: 25px;\n      display: flex;\n      flex-direction: column; }\n      body .code-box .button div {\n        margin-top: 15px;\n        border: 1px solid #1B94DD;\n        padding: 8px;\n        text-align: center;\n        font-size: 14px;\n        background-color: #ecf5ff;\n        color: black;\n        border-radius: 5px; }\n        body .code-box .button div:hover {\n          background-color: #1B94DD; }\n        body .code-box .button div.active {\n          transform: scale(1.1);\n          background-color: #1B94DD; }\n  body .page-box {\n    flex: 1;\n    height: 60vh;\n    border: 1px solid black; }\n","js":"\nvar reloadCSS = require('_css_loader');\nmodule.hot.dispose(reloadCSS);\nmodule.hot.accept(reloadCSS);"},"hash":"0aa204b84cb9ca3adfd65dd983fbc9d5","cacheData":{"env":{}}}